siena3d/__init__.py
siena3d/astrometry.py
siena3d/cube.py
siena3d/data.py
siena3d/header.py
siena3d/parameters.py
siena3d/plot.py
siena3d/spectrum.py
siena3d/data/eline_rf.txt
siena3d/data/logo.png
siena3d/data/logo.txt
siena3d-0.0.3.dist-info/LICENSE
siena3d-0.0.3.dist-info/METADATA
siena3d-0.0.3.dist-info/WHEEL
siena3d-0.0.3.dist-info/top_level.txt
siena3d-0.0.3.dist-info/RECORD
