Metadata-Version: 2.1
Name: siena3d
Version: 0.0.3
Summary: Spectroastrometric analysis tool for Ionised gas Emission in Nearby AGN
Home-page: https://github.com/nicowinkel/Siena3D
Author: Nico Winkel
Author-email: winkel@mpia.de
License: BSD-3-Clause
Classifier: Programming Language :: Python :: 3
Requires-Python: >=3.7
License-File: LICENSE
Requires-Dist: numpy
Requires-Dist: scipy
Requires-Dist: tqdm
Requires-Dist: matplotlib
Requires-Dist: plotly
Requires-Dist: astropy
Requires-Dist: specutils
Requires-Dist: importlib-metadata (>=2.0) ; python_version < "3.7"
Provides-Extra: docs
Requires-Dist: sphinx ; extra == 'docs'
Provides-Extra: test
Requires-Dist: astropy ; extra == 'test'
